iseqmetacreator/__init__.py
iseqmetacreator/create_meta.py
iseqmetacreator/parse_meta.py
iseqmetacreator/wdl_parser.py
iseqmetacreator/resources/fields/inputs-fields.json
iseqmetacreator/resources/fields/outputs-fields.json
iseqmetacreator/resources/fields/workflows-fields.json
iseqmetacreator/test/__init__.py
iseqmetacreator/test/create_meta_test.py
iseqmetamodifier/__init__.py
iseqmetamodifier/converter.py
iseqmetamodifier/test/__init__.py
iseqmetamodifier/test/converter_test.py
iseqspreadsheet/__init__.py
iseqspreadsheet/parse_inputs.py
iseqspreadsheet/parse_outputs.py
iseqspreadsheet/parse_workflows.py
iseqspreadsheet/spreadsheetutils.py
iseqspreadsheet/test/__init__.py
iseqspreadsheet/test/spreadsheetutils_test.py
iseqmetatools-0.0.6.dist-info/LICENSE
iseqmetatools-0.0.6.dist-info/METADATA
iseqmetatools-0.0.6.dist-info/WHEEL
iseqmetatools-0.0.6.dist-info/entry_points.txt
iseqmetatools-0.0.6.dist-info/top_level.txt
iseqmetatools-0.0.6.dist-info/RECORD
